victron_ble2mqtt/__init__.py
victron_ble2mqtt/__main__.py
victron_ble2mqtt/constants.py
victron_ble2mqtt/mqtt.py
victron_ble2mqtt/user_settings.py
victron_ble2mqtt/victron_ble_utils.py
victron_ble2mqtt/cli_app/__init__.py
victron_ble2mqtt/cli_app/debug.py
victron_ble2mqtt/cli_app/mqtt.py
victron_ble2mqtt/cli_app/settings.py
victron_ble2mqtt/cli_app/shell_completion.py
victron_ble2mqtt/cli_app/systemd.py
victron_ble2mqtt/cli_app/update_readme_history.py
victron_ble2mqtt/cli_dev/__init__.py
victron_ble2mqtt/cli_dev/code_style.py
victron_ble2mqtt/cli_dev/packaging.py
victron_ble2mqtt/cli_dev/shell_completion.py
victron_ble2mqtt/cli_dev/testing.py
victron_ble2mqtt/cli_dev/update_readme_history.py
victron_ble2mqtt/tests/__init__.py
victron_ble2mqtt/tests/test_doctests.py
victron_ble2mqtt/tests/test_project_setup.py
victron_ble2mqtt/tests/test_readme.py
victron_ble2mqtt/tests/test_readme_history.py
victron_ble2mqtt-0.7.2.dist-info/METADATA
victron_ble2mqtt-0.7.2.dist-info/WHEEL
victron_ble2mqtt-0.7.2.dist-info/entry_points.txt
victron_ble2mqtt-0.7.2.dist-info/RECORD
