Metadata-Version: 2.4
Name: victron_ble2mqtt
Version: 0.7.2
Summary: Emit MQTT events from victron-ble
Project-URL: Documentation, https://github.com/jedie/victron-ble2mqtt
Project-URL: Source, https://github.com/jedie/victron-ble2mqtt
Author-email: Jens Diemer <git@jensdiemer.de>
License: GPL-3.0-or-later
Requires-Python: >=3.11
Requires-Dist: bx-py-utils
Requires-Dist: cli-base-utilities>=0.17.0
Requires-Dist: ha-services
Requires-Dist: rich
Requires-Dist: tyro
Requires-Dist: victron-ble
